url2env/__init__.py
zerotk_url2env-1.3.5.dist-info/METADATA
zerotk_url2env-1.3.5.dist-info/WHEEL
zerotk_url2env-1.3.5.dist-info/entry_points.txt
zerotk_url2env-1.3.5.dist-info/RECORD
